{
	"info": {
		"_postman_id": "0eca38d2-141d-4b7c-96ea-b62db0d5f425",
		"name": "Отус_ДЗ_2",
		"schema": "https://schema.getpostman.com/json/collection/v2.1.0/collection.json"
	},
	"item": [
		{
			"name": "Список юзеров",
			"request": {
				"method": "GET",
				"header": [],
				"url": {
					"raw": "http://{{baseUrl}}/user",
					"protocol": "http",
					"host": [
						"{{baseUrl}}"
					],
					"path": [
						"user"
					]
				}
			},
			"response": []
		},
		{
			"name": "Добавление юзера",
			"request": {
				"method": "POST",
				"header": [],
				"body": {
					"mode": "raw",
					"raw": "{\"name\": \"Степан\"}",
					"options": {
						"raw": {
							"language": "json"
						}
					}
				},
				"url": {
					"raw": "http://{{baseUrl}}/user",
					"protocol": "http",
					"host": [
						"{{baseUrl}}"
					],
					"path": [
						"user"
					]
				}
			},
			"response": []
		},
		{
			"name": "Изменить юзера",
			"request": {
				"method": "PUT",
				"header": [],
				"body": {
					"mode": "raw",
					"raw": "{\r\n    \"name\": \"СТАС\"\r\n}",
					"options": {
						"raw": {
							"language": "json"
						}
					}
				},
				"url": {
					"raw": "http://{{baseUrl}}/user/4",
					"protocol": "http",
					"host": [
						"{{baseUrl}}"
					],
					"path": [
						"user",
						"4"
					]
				}
			},
			"response": []
		},
		{
			"name": "Получить юзера",
			"request": {
				"method": "GET",
				"header": [],
				"url": {
					"raw": "http://{{baseUrl}}/user/6",
					"protocol": "http",
					"host": [
						"{{baseUrl}}"
					],
					"path": [
						"user",
						"6"
					]
				}
			},
			"response": []
		},
		{
			"name": "Удалить юзера",
			"request": {
				"method": "DELETE",
				"header": [],
				"url": {
					"raw": "http://{{baseUrl}}/user/6",
					"protocol": "http",
					"host": [
						"{{baseUrl}}"
					],
					"path": [
						"user",
						"6"
					]
				}
			},
			"response": []
		}
	],
	"event": [
		{
			"listen": "prerequest",
			"script": {
				"type": "text/javascript",
				"exec": [
					""
				]
			}
		},
		{
			"listen": "test",
			"script": {
				"type": "text/javascript",
				"exec": [
					""
				]
			}
		}
	],
	"variable": [
		{
			"key": "baseUrl",
			"value": "arch.homework"
		}
	]
}